{
  "reviewer": "auditor",
  "branch": "runtime2-builder-v2-identity",
  "timestamp": "2026-03-19T13:00:00Z",
  "reviewed_version": "v2",
  "summary": "All major/minor findings from v1 resolved by coder v6. IdentityData.ResolveDefault() has try/catch, Export uses GetOrCreateDefaultAsync (consistent with Get), Data.Envelope has SensitivePropertyFilter. 1649 tests pass. No test for ResolveDefault failure path (hard to arrange without test infra), accepted. Verdict: PASS.",
  "previous_reviews_assessed": {
    "codeanalyzer": "agree — v3 findings remain valid and resolved",
    "tester": "agree — v4 approval still holds, coder v6 changes don't regress tested paths",
    "security": "agree — finding #3 (Envelope gap) now fixed"
  },
  "findings": [
    {
      "id": 1,
      "severity": "major",
      "category": "cross-file",
      "file": "PLang/Runtime2/modules/identity/IdentityData.cs",
      "line": 52,
      "issue": "[RESOLVED] GetOrCreateDefaultAsync throws on save failure. ResolveDefault() now has try/catch, returns null.",
      "missed_by": "codeanalyzer",
      "impact": "Previously: unhandled crash on %MyIdentity% access. Now: graceful null.",
      "suggestion": "Resolved. No test for failure path (accepted — hard to arrange)."
    },
    {
      "id": 2,
      "severity": "minor",
      "category": "cross-file",
      "file": "PLang/Runtime2/modules/identity/export.cs",
      "line": 30,
      "issue": "[RESOLVED] Export now uses GetOrCreateDefaultAsync, consistent with Get.",
      "missed_by": "none",
      "impact": "Previously: Export(null) returned NotFound when identities existed but no default. Now: promotes/auto-creates like Get.",
      "suggestion": "Resolved. Test updated to expect auto-create."
    },
    {
      "id": 3,
      "severity": "minor",
      "category": "foundation",
      "file": "PLang/Runtime2/Engine/Memory/Data.Envelope.cs",
      "line": 29,
      "issue": "[RESOLVED] SensitivePropertyFilter.Filter added to _envelopeJsonOptions.",
      "missed_by": "none",
      "impact": "Defense-in-depth: future Compress() calls won't leak [Sensitive] properties.",
      "suggestion": "Resolved."
    },
    {
      "id": 4,
      "severity": "minor",
      "category": "cross-file",
      "file": "PLang/Runtime2/modules/identity/rename.cs",
      "line": 39,
      "issue": "[ACCEPTED] Rename partial failure leaves orphaned entry. Known limitation — needs transactional DataSource.",
      "missed_by": "none",
      "impact": "Very low probability. Not fixable without DataSource transactions.",
      "suggestion": "Track as future improvement when DataSource gets transaction support."
    }
  ]
}
